nonebot_plugin_lingyi_chat/__init__.py
nonebot_plugin_lingyi_chat/config.py
nonebot_plugin_lingyi_chat-0.1.4.dist-info/LICENSE
nonebot_plugin_lingyi_chat-0.1.4.dist-info/METADATA
nonebot_plugin_lingyi_chat-0.1.4.dist-info/WHEEL
nonebot_plugin_lingyi_chat-0.1.4.dist-info/RECORD
