Metadata-Version: 2.1
Name: nonebot-plugin-lingyi-chat
Version: 0.1.4
Summary: 
Author: Yeying-Xingchen
Author-email: yeyingxingchen@yeah.net
Requires-Python: >=3.12,<4.0
Classifier: Programming Language :: Python :: 3
Classifier: Programming Language :: Python :: 3.12
Requires-Dist: aiohttp (>=3.10.9,<4.0.0)
Requires-Dist: nonebot2 (>=2.2.0,<3.0.0)
